{
  "$id": "https://www.onlyf1.com/db/schema/v3.1.0/splitted/onlyf1-db-entrants.schema.json",
  "$schema": "http://json-schema.org/draft-07/schema",
  "title": "OnlyF1-DB",
  "description": "OnlyF1-DB Entrants JSON Schema",
  "type": "array",
  "items": {
    "$ref": "#/definitions/Entrant"
  },
  "additionalProperties": false,
  "definitions": {
    "Entrant": {
      "type": "object",
      "additionalProperties": false,
      "properties": {
        "id": {
          "type": "string",
          "description": "The unique identifier."
        },
        "name": {
          "type": "string",
          "description": "The name."
        }
      },
      "required": [
        "id",
        "name"
      ]
    }
  }
}
